jokyjokes/__init__.py
jokyjokes/chucknorris.py
jokyjokes/topkek.py
jokyjokes/yomama.py
jokyjokes-0.0.4.dist-info/DESCRIPTION.rst
jokyjokes-0.0.4.dist-info/METADATA
jokyjokes-0.0.4.dist-info/RECORD
jokyjokes-0.0.4.dist-info/WHEEL
jokyjokes-0.0.4.dist-info/metadata.json
jokyjokes-0.0.4.dist-info/top_level.txt
tests/__init__.py
tests/test_chucknorris.py
tests/test_topkek.py
tests/test_yomama.py
