Metadata-Version: 2.0
Name: jokyjokes
Version: 0.0.4
Summary: A package that provides you hundreds of terrbile jokes
Home-page: https://github.com/demirantay/jokes
Author: Demir Antay
Author-email: demir99antay@gmail.com
License: UNKNOWN
Platform: UNKNOWN
